README.md
setup.cfg
setup.py
Southxchange/__init__.py
Southxchange.egg-info/PKG-INFO
Southxchange.egg-info/SOURCES.txt
Southxchange.egg-info/dependency_links.txt
Southxchange.egg-info/requires.txt
Southxchange.egg-info/top_level.txt