Metadata-Version: 1.0
Name: Southxchange
Version: 1.3
Summary: Southxchange
Home-page: https://github.com/Zenitsudeck/Southxchange
Author: Zenitsudeck
Author-email: UNKNOWN
License: UNKNOWN
Platform: UNKNOWN
